{
  "file": "2024-04-08_17-37-45_cycling_14797816704.fit",
  "activity_type": "cycling",
  "is_indoor": false,
  "duration": "23m 44s",
  "duration_s": 1424,
  "distance_km": 7.61,
  "elevation_m": 63,
  "calories_kcal": 190,
  "heart_rate": {
    "avg_bpm": 107,
    "max_bpm": 130,
    "min_bpm": 76,
    "avg_hrr_pct": 49.2
  },
  "hr_zones_pct": {
    "Z1 Recovery": 76.9,
    "Z2 Endurance": 23.1,
    "Z3 Tempo": 0.0,
    "Z4 Threshold": 0.0,
    "Z5 VO2max": 0.0
  },
  "cadence": {
    "avg_rpm": null,
    "max_rpm": null
  },
  "avg_speed_kph": 19.6,
  "max_speed_kph": 24.4
}