{
  "file": "2024-07-10_15-55-51_cycling_16345378487.fit",
  "activity_type": "cycling",
  "is_indoor": false,
  "duration": "24m 10s",
  "duration_s": 1451,
  "distance_km": 7.6,
  "elevation_m": 56,
  "calories_kcal": 158,
  "heart_rate": {
    "avg_bpm": 98,
    "max_bpm": 123,
    "min_bpm": 70,
    "avg_hrr_pct": 42.3
  },
  "hr_zones_pct": {
    "Z1 Recovery": 86.5,
    "Z2 Endurance": 13.5,
    "Z3 Tempo": 0.0,
    "Z4 Threshold": 0.0,
    "Z5 VO2max": 0.0
  },
  "cadence": {
    "avg_rpm": null,
    "max_rpm": null
  },
  "avg_speed_kph": 18.5,
  "max_speed_kph": 32.8
}