{
  "file": "2025-05-12_10-04-06_cycling_19100287091.fit",
  "activity_type": "road_biking",
  "is_indoor": false,
  "duration": "3h 57m 23s",
  "duration_s": 14243,
  "distance_km": 65.91,
  "elevation_m": 900,
  "calories_kcal": 1629,
  "heart_rate": {
    "avg_bpm": 104,
    "max_bpm": 156,
    "min_bpm": 56,
    "avg_hrr_pct": 46.9
  },
  "hr_zones_pct": {
    "Z1 Recovery": 68.8,
    "Z2 Endurance": 24.2,
    "Z3 Tempo": 4.3,
    "Z4 Threshold": 2.6,
    "Z5 VO2max": 0.0
  },
  "cadence": {
    "avg_rpm": 66,
    "max_rpm": 131
  },
  "avg_speed_kph": 21.5,
  "max_speed_kph": 44.7,
  "avg_power_w": 163.2,
  "max_power_w": 709,
  "norm_power_w": 190.0,
  "intensity_factor": 0.64,
  "tss": 161.9,
  "ftp_used_w": 297,
  "w_per_kg": 2.4,
  "np_per_kg": 2.79
}